agentbill_crewai/__init__.py
agentbill_crewai/exceptions.py
agentbill_crewai/orders.py
agentbill_crewai/signals.py
agentbill_crewai/tracing.py
agentbill_crewai/tracker.py
agentbill_py_crewai-7.17.3.dist-info/METADATA
agentbill_py_crewai-7.17.3.dist-info/WHEEL
agentbill_py_crewai-7.17.3.dist-info/top_level.txt
agentbill_py_crewai-7.17.3.dist-info/RECORD
