Metadata-Version: 2.4
Name: agentbill-py-crewai
Version: 7.17.3
Summary: AgentBill integration for CrewAI - Zero-config crew tracking
Home-page: https://agentbill.io
Author: AgentBill
Author-email: AgentBill <support@agentbill.io>
License: MIT
Project-URL: Homepage, https://agentbill.io
Project-URL: Documentation, https://docs.agentbill.io
Keywords: crewai,ai,agent,billing,usage-tracking,agentbill,crew
Classifier: Development Status :: 5 - Production/Stable
Classifier: Intended Audience :: Developers
Classifier: License :: OSI Approved :: MIT License
Classifier: Programming Language :: Python :: 3
Classifier: Programming Language :: Python :: 3.8
Classifier: Programming Language :: Python :: 3.9
Classifier: Programming Language :: Python :: 3.10
Classifier: Programming Language :: Python :: 3.11
Classifier: Programming Language :: Python :: 3.12
Classifier: Topic :: Software Development :: Libraries :: Python Modules
Classifier: Topic :: Scientific/Engineering :: Artificial Intelligence
Requires-Python: >=3.8
Requires-Dist: crewai>=0.1.0
Requires-Dist: requests>=2.25.0
Provides-Extra: dev
Requires-Dist: pytest>=7.0.0; extra == "dev"
Requires-Dist: pytest-cov>=4.0.0; extra == "dev"
Requires-Dist: pylint>=2.15.0; extra == "dev"
Requires-Dist: black>=22.0.0; extra == "dev"
Dynamic: author
Dynamic: home-page
Dynamic: requires-python
